<?xml version="1.0" encoding="UTF-8" standalone="no"?>
<configuration>
	<feature name="JogoSerio"/>
	<feature name="Boi"/>
	<feature name="Boi_Peso"/>
	<feature name="Boi_Peso_Gordo"/>
	<feature name="Boi_Peso_Magro"/>
	<feature name="Boi_Saude"/>
	<feature name="Boi_Sad_Normal"/>
	<feature name="Boi_Sad_Doente"/>
	<feature name="Boi_Sad_Tratamento"/>
	<feature name="Piquete"/>
	<feature name="Piq_Condicao"/>
	<feature name="Piq_Cond_Normal"/>
	<feature name="Piq_Cond_Danificado"/>
	<feature name="Piq_Lotacao"/>
	<feature name="Piq_Lot_Alta"/>
	<feature name="Piq_Lot_Media"/>
	<feature name="Piq_Lot_Baixa"/>
	<feature name="Gramínea"/>
	<feature name="Gram_Tamanho"/>
	<feature name="Gram_Tam_Alta"/>
	<feature name="Gram_Tam_Media"/>
	<feature name="Gram_Tam_Baixa"/>
	<feature name="Gram_Coloracao"/>
	<feature name="Gram_Col_Verde"/>
	<feature name="Gram_Col_Amarela"/>
	<feature name="Cocho"/>
	<feature name="Cocho_Cheio"/>
	<feature name="Cocho_Vazio"/>
	<feature name="Tanque"/>
	<feature name="Tan_Cheio"/>
	<feature name="Tan_Vazio"/>
	<feature name="Mangueiro"/>
	<feature name="Man_Disponivel"/>
	<feature name="Man_Ocupado"/>
	<feature name="Area"/>
	<feature name="Area_Disponivel"/>
	<feature name="Area_Disp_Embarque"/>
	<feature name="Area_Disp_Desembarque"/>
	<feature name="Area_Ocupado"/>
	<feature name="Area_Ocup_Embarque"/>
	<feature name="Area_Ocup_Desembarque"/>
	<feature name="Manejo"/>
	<feature name="Sede"/>
	<feature name="Estacao"/>
	<feature name="Est_Primavera"/>
	<feature name="Est_Outono"/>
	<feature name="Est_Inverno"/>
	<feature name="Est_Verao"/>
</configuration>
